report_pdf_wrapper/__init__.py
report_pdf_wrapper/report_pdf_wrapper.py
report_pdf_wrapper-1.0.7.dist-info/LICENSE
report_pdf_wrapper-1.0.7.dist-info/METADATA
report_pdf_wrapper-1.0.7.dist-info/WHEEL
report_pdf_wrapper-1.0.7.dist-info/top_level.txt
report_pdf_wrapper-1.0.7.dist-info/RECORD
